{
  "id": "e01fc762-5f65-41af-b75c-c1c7e87106de",
  "prevId": "657a4e3c-830c-4357-9d8e-f7025e32b4ae",
  "version": "7",
  "dialect": "postgresql",
  "tables": {
    "public.space_table": {
      "name": "space_table",
      "schema": "",
      "columns": {
        "id": {
          "name": "id",
          "type": "text",
          "primaryKey": true,
          "notNull": true
        },
        "spaceUrl": {
          "name": "spaceUrl",
          "type": "text",
          "primaryKey": false,
          "notNull": true
        },
        "user_id": {
          "name": "user_id",
          "type": "text",
          "primaryKey": false,
          "notNull": true
        }
      },
      "indexes": {},
      "foreignKeys": {
        "space_table_user_id_user_id_fk": {
          "name": "space_table_user_id_user_id_fk",
          "tableFrom": "space_table",
          "tableTo": "user",
          "columnsFrom": [
            "user_id"
          ],
          "columnsTo": [
            "id"
          ],
          "onDelete": "cascade",
          "onUpdate": "no action"
        }
      },
      "compositePrimaryKeys": {},
      "uniqueConstraints": {}
    },
    "public.user": {
      "name": "user",
      "schema": "",
      "columns": {
        "id": {
          "name": "id",
          "type": "text",
          "primaryKey": true,
          "notNull": true
        },
        "username": {
          "name": "username",
          "type": "text",
          "primaryKey": false,
          "notNull": true
        },
        "email": {
          "name": "email",
          "type": "text",
          "primaryKey": false,
          "notNull": true
        }
      },
      "indexes": {},
      "foreignKeys": {},
      "compositePrimaryKeys": {},
      "uniqueConstraints": {
        "user_id_unique": {
          "name": "user_id_unique",
          "nullsNotDistinct": false,
          "columns": [
            "id"
          ]
        },
        "user_username_unique": {
          "name": "user_username_unique",
          "nullsNotDistinct": false,
          "columns": [
            "username"
          ]
        },
        "user_email_unique": {
          "name": "user_email_unique",
          "nullsNotDistinct": false,
          "columns": [
            "email"
          ]
        }
      }
    }
  },
  "enums": {},
  "schemas": {},
  "_meta": {
    "columns": {},
    "schemas": {},
    "tables": {}
  }
}